lemniscat/runtime/__init__.py
lemniscat/runtime/lem.py
lemniscat/runtime/version.py
lemniscat/runtime/engine/__init__.py
lemniscat/runtime/engine/engine_manifest.py
lemniscat/runtime/engine/engine_runtime.py
lemniscat/runtime/engine/engine_variables.py
lemniscat/runtime/model/__init__.py
lemniscat/runtime/model/models.py
lemniscat/runtime/plugin/__init__.py
lemniscat/runtime/plugin/pluginmanager.py
lemniscat/runtime/plugin/utilities.py
lemniscat_runtime-0.13.0.dist-info/licenses/LICENSE
lemniscat_runtime-0.13.0.dist-info/METADATA
lemniscat_runtime-0.13.0.dist-info/WHEEL
lemniscat_runtime-0.13.0.dist-info/entry_points.txt
lemniscat_runtime-0.13.0.dist-info/top_level.txt
lemniscat_runtime-0.13.0.dist-info/RECORD
