Metadata-Version: 2.4
Name: lemniscat.runtime
Version: 0.13.0
Summary: A runtime to provide product oriented in DevOps approach
Author-email: Philippe MORISSEAU <philippe.morisseau@outlook.com>
License: MIT
Project-URL: Homepage, https://github.com/lemniscat-devops/lemniscat.runtime
Project-URL: Issues, https://github.com/lemniscat-devops/lemniscat.runtime/issues
Classifier: Programming Language :: Python :: 3
Classifier: License :: OSI Approved :: MIT License
Classifier: Operating System :: OS Independent
Requires-Python: >=3.10
License-File: LICENSE
Requires-Dist: PyYAML==6.0.1
Requires-Dist: packaging==23.2
Requires-Dist: dacite==1.8.1
Requires-Dist: lemniscat.core>=0.3.1
Dynamic: license-file
